{"variable":[{"key":"SERVER_URL","value":"https:\/\/ballywulff.thecloudgroup.tech"},{"key":"LOCAL_URL","value":"http:\/\/localhost:8022"}],"info":{"_postman_id":"e0c0902c-6237-46a3-839a-8aa8097d3670","name":"2024_02_15_PM_ballywulff_collection.json","schema":"https:\/\/schema.getpostman.com\/json\/collection\/v2.1.0\/collection.json","_exporter_id":"14065338","_collection_link":"https:\/\/red-meteor-677589.postman.co\/workspace\/ballyWulff~623fb7cc-23c1-46de-8ac4-a61a5894f32e\/collection\/14065338-e0c0902c-6237-46a3-839a-8aa8097d3670?action=share&source=collection_link&creator=14065338"},"item":[{"name":"auth","item":[{"name":"SERVER_api\/auth\/login","request":{"method":"POST","header":[{"key":"Accept","value":"application\/json"},{"key":"Content-Type","value":"application\/json"},{"key":"x-lang","value":"es"}],"url":{"raw":"{{SERVER_URL}}\/api\/auth\/login","host":"{{SERVER_URL}}","path":["api","auth","login"],"variable":[]},"auth":{"type":"noauth"},"body":{"mode":"raw","raw":"{\"email\":\"superadmin@test.com\",\"password\":\"Pruebas123*\"}","options":{"raw":{"language":"json"}}}},"event":[{"script":{"exec":["pm.collectionVariables.set('TOKEN_SERVER',pm.response.json().data)"]}}]},{"name":"SERVER_api\/auth\/logout","request":{"method":"POST","header":[{"key":"Accept","value":"application\/json"},{"key":"Content-Type","value":"application\/json"},{"key":"x-lang","value":"es"}],"url":{"raw":"{{SERVER_URL}}\/api\/auth\/login","host":"{{SERVER_URL}}","path":["api","auth","logout"],"variable":[]},"auth":{"type":"bearer","bearer":[{"key":"token","value":"{{TOKEN_SERVER}}","type":"string"}]},"body":{"mode":"raw","raw":"\"{}\"","options":{"raw":{"language":"json"}}}},"event":[]},{"name":"SERVER_api\/auth\/me","request":{"method":"GET","header":[{"key":"Accept","value":"application\/json"},{"key":"Content-Type","value":"application\/json"},{"key":"x-lang","value":"es"}],"url":{"raw":"{{SERVER_URL}}\/api\/auth\/login","host":"{{SERVER_URL}}","path":["api","auth","me"],"variable":[]},"auth":{"type":"bearer","bearer":[{"key":"token","value":"{{TOKEN_SERVER}}","type":"string"}]},"body":{"mode":"raw","raw":"\"{}\"","options":{"raw":{"language":"json"}}}},"event":[]},{"name":"SERVER_api\/auth\/register","request":{"method":"POST","header":[{"key":"Accept","value":"application\/json"},{"key":"Content-Type","value":"application\/json"},{"key":"x-lang","value":"es"}],"url":{"raw":"{{SERVER_URL}}\/api\/auth\/login","host":"{{SERVER_URL}}","path":["api","auth","register"],"variable":[]},"auth":{"type":"bearer","bearer":[{"key":"token","value":"{{TOKEN_SERVER}}","type":"string"}]},"body":{"mode":"raw","raw":"{\"name\":\"{{$randomFirstName}}\",\"lastname\":\"{{$randomLastName}}\",\"email\":\"{{$randomExampleEmail}}\",\"address\":\"{{$randomStreetAddress}}\",\"member_number\":\"{{$randomInt}}\",\"city_id\":\"{{$randomInt}}\",\"state_id\":\"{{INT10}}\",\"country_id\":\"{{INT10}}\",\"language\":\"en\"}","options":{"raw":{"language":"json"}}}},"event":[]},{"name":"api\/auth\/login","request":{"method":"POST","header":[{"key":"Accept","value":"application\/json"},{"key":"Content-Type","value":"application\/json"},{"key":"x-lang","value":"es"}],"url":{"raw":"{{LOCAL_URL}}\/api\/auth\/login","host":"{{LOCAL_URL}}","path":["api","auth","login"],"variable":[]},"auth":{"type":"noauth"},"body":{"mode":"raw","raw":"{\"email\":\"superadmin@test.com\",\"password\":\"Pruebas123*\"}","options":{"raw":{"language":"json"}}}},"event":[{"script":{"exec":["pm.collectionVariables.set('TOKEN',pm.response.json().data)"]}}]},{"name":"api\/auth\/logout","request":{"method":"POST","header":[{"key":"Accept","value":"application\/json"},{"key":"Content-Type","value":"application\/json"},{"key":"x-lang","value":"es"}],"url":{"raw":"{{LOCAL_URL}}\/api\/auth\/login","host":"{{LOCAL_URL}}","path":["api","auth","logout"],"variable":[]},"auth":{"type":"bearer","bearer":[{"key":"token","value":"{{TOKEN}}","type":"string"}]},"body":{"mode":"raw","raw":"\"{}\"","options":{"raw":{"language":"json"}}}},"event":[]},{"name":"api\/auth\/me","request":{"method":"GET","header":[{"key":"Accept","value":"application\/json"},{"key":"Content-Type","value":"application\/json"},{"key":"x-lang","value":"es"}],"url":{"raw":"{{LOCAL_URL}}\/api\/auth\/login","host":"{{LOCAL_URL}}","path":["api","auth","me"],"variable":[]},"auth":{"type":"bearer","bearer":[{"key":"token","value":"{{TOKEN}}","type":"string"}]},"body":{"mode":"raw","raw":"\"{}\"","options":{"raw":{"language":"json"}}}},"event":[]},{"name":"api\/auth\/register","request":{"method":"POST","header":[{"key":"Accept","value":"application\/json"},{"key":"Content-Type","value":"application\/json"},{"key":"x-lang","value":"es"}],"url":{"raw":"{{LOCAL_URL}}\/api\/auth\/login","host":"{{LOCAL_URL}}","path":["api","auth","register"],"variable":[]},"auth":{"type":"bearer","bearer":[{"key":"token","value":"{{TOKEN}}","type":"string"}]},"body":{"mode":"raw","raw":"{\"name\":\"{{$randomFirstName}}\",\"lastname\":\"{{$randomLastName}}\",\"email\":\"{{$randomExampleEmail}}\",\"address\":\"{{$randomStreetAddress}}\",\"member_number\":\"{{$randomInt}}\",\"city_id\":\"{{$randomInt}}\",\"state_id\":\"{{INT10}}\",\"country_id\":\"{{INT10}}\",\"language\":\"en\"}","options":{"raw":{"language":"json"}}}},"event":[]}]},{"name":"country","item":[{"name":"SERVER_api\/country","request":{"method":"GET","header":[{"key":"Accept","value":"application\/json"},{"key":"Content-Type","value":"application\/json"},{"key":"x-lang","value":"es"}],"url":{"raw":"{{SERVER_URL}}\/api\/auth\/login","host":"{{SERVER_URL}}","path":["api","country"],"variable":[]},"auth":{"type":"bearer","bearer":[{"key":"token","value":"{{TOKEN_SERVER}}","type":"string"}]},"body":{"mode":"raw","raw":"\"{}\"","options":{"raw":{"language":"json"}}}},"event":[]},{"name":"SERVER_api\/country","request":{"method":"POST","header":[{"key":"Accept","value":"application\/json"},{"key":"Content-Type","value":"application\/json"},{"key":"x-lang","value":"es"}],"url":{"raw":"{{SERVER_URL}}\/api\/auth\/login","host":"{{SERVER_URL}}","path":["api","country"],"variable":[]},"auth":{"type":"bearer","bearer":[{"key":"token","value":"{{TOKEN_SERVER}}","type":"string"}]},"body":{"mode":"raw","raw":"{\"json_id\":\"{{INT10}}\",\"name\":\"{{$randomLoremParagraph}}\",\"iso3\":\"{{$randomLoremParagraph}}\",\"iso2\":\"{{$randomLoremParagraph}}\",\"numeric_code\":\"{{$randomLoremParagraph}}\",\"phone_code\":\"{{$randomLoremParagraph}}\",\"capital\":\"{{$randomLoremParagraph}}\",\"currency\":\"{{$randomLoremParagraph}}\",\"currency_symbol\":\"{{$randomLoremParagraph}}\",\"tld\":\"{{$randomLoremParagraph}}\",\"native\":\"{{$randomLoremParagraph}}\",\"region\":\"{{$randomLoremParagraph}}\",\"subregion\":\"{{$randomLoremParagraph}}\",\"timezones\":\"\",\"translations\":\"\",\"languages\":\"\",\"latitude\":\"{{$randomLoremParagraph}}\",\"longitude\":\"{{$randomLoremParagraph}}\",\"emoji\":\"{{$randomLoremParagraph}}\",\"emojiU\":\"{{$randomLoremParagraph}}\"}","options":{"raw":{"language":"json"}}}},"event":[]},{"name":"SERVER_api\/country\/{country}","request":{"method":"DELETE","header":[{"key":"Accept","value":"application\/json"},{"key":"Content-Type","value":"application\/json"},{"key":"x-lang","value":"es"}],"url":{"raw":"{{SERVER_URL}}\/api\/auth\/login","host":"{{SERVER_URL}}","path":["api","country",":country"],"variable":[]},"auth":{"type":"bearer","bearer":[{"key":"token","value":"{{TOKEN_SERVER}}","type":"string"}]},"body":{"mode":"raw","raw":"\"{}\"","options":{"raw":{"language":"json"}}}},"event":[]},{"name":"SERVER_api\/country\/{country}","request":{"method":"GET","header":[{"key":"Accept","value":"application\/json"},{"key":"Content-Type","value":"application\/json"},{"key":"x-lang","value":"es"}],"url":{"raw":"{{SERVER_URL}}\/api\/auth\/login","host":"{{SERVER_URL}}","path":["api","country",":country"],"variable":[]},"auth":{"type":"bearer","bearer":[{"key":"token","value":"{{TOKEN_SERVER}}","type":"string"}]},"body":{"mode":"raw","raw":"\"{}\"","options":{"raw":{"language":"json"}}}},"event":[]},{"name":"SERVER_api\/country\/{country}","request":{"method":"PATCH","header":[{"key":"Accept","value":"application\/json"},{"key":"Content-Type","value":"application\/json"},{"key":"x-lang","value":"es"}],"url":{"raw":"{{SERVER_URL}}\/api\/auth\/login","host":"{{SERVER_URL}}","path":["api","country",":country"],"variable":[]},"auth":{"type":"bearer","bearer":[{"key":"token","value":"{{TOKEN_SERVER}}","type":"string"}]},"body":{"mode":"raw","raw":"\"{}\"","options":{"raw":{"language":"json"}}}},"event":[]},{"name":"SERVER_api\/country\/{country}","request":{"method":"PUT","header":[{"key":"Accept","value":"application\/json"},{"key":"Content-Type","value":"application\/json"},{"key":"x-lang","value":"es"}],"url":{"raw":"{{SERVER_URL}}\/api\/auth\/login","host":"{{SERVER_URL}}","path":["api","country",":country"],"variable":[]},"auth":{"type":"bearer","bearer":[{"key":"token","value":"{{TOKEN_SERVER}}","type":"string"}]},"body":{"mode":"raw","raw":"\"{}\"","options":{"raw":{"language":"json"}}}},"event":[]},{"name":"api\/country","request":{"method":"GET","header":[{"key":"Accept","value":"application\/json"},{"key":"Content-Type","value":"application\/json"},{"key":"x-lang","value":"es"}],"url":{"raw":"{{LOCAL_URL}}\/api\/auth\/login","host":"{{LOCAL_URL}}","path":["api","country"],"variable":[]},"auth":{"type":"bearer","bearer":[{"key":"token","value":"{{TOKEN}}","type":"string"}]},"body":{"mode":"raw","raw":"\"{}\"","options":{"raw":{"language":"json"}}}},"event":[]},{"name":"api\/country","request":{"method":"POST","header":[{"key":"Accept","value":"application\/json"},{"key":"Content-Type","value":"application\/json"},{"key":"x-lang","value":"es"}],"url":{"raw":"{{LOCAL_URL}}\/api\/auth\/login","host":"{{LOCAL_URL}}","path":["api","country"],"variable":[]},"auth":{"type":"bearer","bearer":[{"key":"token","value":"{{TOKEN}}","type":"string"}]},"body":{"mode":"raw","raw":"{\"json_id\":\"{{INT10}}\",\"name\":\"{{$randomLoremParagraph}}\",\"iso3\":\"{{$randomLoremParagraph}}\",\"iso2\":\"{{$randomLoremParagraph}}\",\"numeric_code\":\"{{$randomLoremParagraph}}\",\"phone_code\":\"{{$randomLoremParagraph}}\",\"capital\":\"{{$randomLoremParagraph}}\",\"currency\":\"{{$randomLoremParagraph}}\",\"currency_symbol\":\"{{$randomLoremParagraph}}\",\"tld\":\"{{$randomLoremParagraph}}\",\"native\":\"{{$randomLoremParagraph}}\",\"region\":\"{{$randomLoremParagraph}}\",\"subregion\":\"{{$randomLoremParagraph}}\",\"timezones\":\"\",\"translations\":\"\",\"languages\":\"\",\"latitude\":\"{{$randomLoremParagraph}}\",\"longitude\":\"{{$randomLoremParagraph}}\",\"emoji\":\"{{$randomLoremParagraph}}\",\"emojiU\":\"{{$randomLoremParagraph}}\"}","options":{"raw":{"language":"json"}}}},"event":[]},{"name":"api\/country\/{country}","request":{"method":"DELETE","header":[{"key":"Accept","value":"application\/json"},{"key":"Content-Type","value":"application\/json"},{"key":"x-lang","value":"es"}],"url":{"raw":"{{LOCAL_URL}}\/api\/auth\/login","host":"{{LOCAL_URL}}","path":["api","country",":country"],"variable":[]},"auth":{"type":"bearer","bearer":[{"key":"token","value":"{{TOKEN}}","type":"string"}]},"body":{"mode":"raw","raw":"\"{}\"","options":{"raw":{"language":"json"}}}},"event":[]},{"name":"api\/country\/{country}","request":{"method":"GET","header":[{"key":"Accept","value":"application\/json"},{"key":"Content-Type","value":"application\/json"},{"key":"x-lang","value":"es"}],"url":{"raw":"{{LOCAL_URL}}\/api\/auth\/login","host":"{{LOCAL_URL}}","path":["api","country",":country"],"variable":[]},"auth":{"type":"bearer","bearer":[{"key":"token","value":"{{TOKEN}}","type":"string"}]},"body":{"mode":"raw","raw":"\"{}\"","options":{"raw":{"language":"json"}}}},"event":[]},{"name":"api\/country\/{country}","request":{"method":"PATCH","header":[{"key":"Accept","value":"application\/json"},{"key":"Content-Type","value":"application\/json"},{"key":"x-lang","value":"es"}],"url":{"raw":"{{LOCAL_URL}}\/api\/auth\/login","host":"{{LOCAL_URL}}","path":["api","country",":country"],"variable":[]},"auth":{"type":"bearer","bearer":[{"key":"token","value":"{{TOKEN}}","type":"string"}]},"body":{"mode":"raw","raw":"\"{}\"","options":{"raw":{"language":"json"}}}},"event":[]},{"name":"api\/country\/{country}","request":{"method":"PUT","header":[{"key":"Accept","value":"application\/json"},{"key":"Content-Type","value":"application\/json"},{"key":"x-lang","value":"es"}],"url":{"raw":"{{LOCAL_URL}}\/api\/auth\/login","host":"{{LOCAL_URL}}","path":["api","country",":country"],"variable":[]},"auth":{"type":"bearer","bearer":[{"key":"token","value":"{{TOKEN}}","type":"string"}]},"body":{"mode":"raw","raw":"\"{}\"","options":{"raw":{"language":"json"}}}},"event":[]}]},{"name":"currency","item":[{"name":"SERVER_api\/currency","request":{"method":"GET","header":[{"key":"Accept","value":"application\/json"},{"key":"Content-Type","value":"application\/json"},{"key":"x-lang","value":"es"}],"url":{"raw":"{{SERVER_URL}}\/api\/auth\/login","host":"{{SERVER_URL}}","path":["api","currency"],"variable":[]},"auth":{"type":"bearer","bearer":[{"key":"token","value":"{{TOKEN_SERVER}}","type":"string"}]},"body":{"mode":"raw","raw":"\"{}\"","options":{"raw":{"language":"json"}}}},"event":[]},{"name":"SERVER_api\/currency","request":{"method":"POST","header":[{"key":"Accept","value":"application\/json"},{"key":"Content-Type","value":"application\/json"},{"key":"x-lang","value":"es"}],"url":{"raw":"{{SERVER_URL}}\/api\/auth\/login","host":"{{SERVER_URL}}","path":["api","currency"],"variable":[]},"auth":{"type":"bearer","bearer":[{"key":"token","value":"{{TOKEN_SERVER}}","type":"string"}]},"body":{"mode":"raw","raw":"{\"name\":\"{{$randomWords}}\",\"code\":\"{{$randomCountryCode}}\"}","options":{"raw":{"language":"json"}}}},"event":[]},{"name":"SERVER_api\/currency\/{currency}","request":{"method":"DELETE","header":[{"key":"Accept","value":"application\/json"},{"key":"Content-Type","value":"application\/json"},{"key":"x-lang","value":"es"}],"url":{"raw":"{{SERVER_URL}}\/api\/auth\/login","host":"{{SERVER_URL}}","path":["api","currency",":currency"],"variable":[]},"auth":{"type":"bearer","bearer":[{"key":"token","value":"{{TOKEN_SERVER}}","type":"string"}]},"body":{"mode":"raw","raw":"\"{}\"","options":{"raw":{"language":"json"}}}},"event":[]},{"name":"SERVER_api\/currency\/{currency}","request":{"method":"GET","header":[{"key":"Accept","value":"application\/json"},{"key":"Content-Type","value":"application\/json"},{"key":"x-lang","value":"es"}],"url":{"raw":"{{SERVER_URL}}\/api\/auth\/login","host":"{{SERVER_URL}}","path":["api","currency",":currency"],"variable":[]},"auth":{"type":"bearer","bearer":[{"key":"token","value":"{{TOKEN_SERVER}}","type":"string"}]},"body":{"mode":"raw","raw":"\"{}\"","options":{"raw":{"language":"json"}}}},"event":[]},{"name":"SERVER_api\/currency\/{currency}","request":{"method":"PATCH","header":[{"key":"Accept","value":"application\/json"},{"key":"Content-Type","value":"application\/json"},{"key":"x-lang","value":"es"}],"url":{"raw":"{{SERVER_URL}}\/api\/auth\/login","host":"{{SERVER_URL}}","path":["api","currency",":currency"],"variable":[]},"auth":{"type":"bearer","bearer":[{"key":"token","value":"{{TOKEN_SERVER}}","type":"string"}]},"body":{"mode":"raw","raw":"\"{}\"","options":{"raw":{"language":"json"}}}},"event":[]},{"name":"SERVER_api\/currency\/{currency}","request":{"method":"PUT","header":[{"key":"Accept","value":"application\/json"},{"key":"Content-Type","value":"application\/json"},{"key":"x-lang","value":"es"}],"url":{"raw":"{{SERVER_URL}}\/api\/auth\/login","host":"{{SERVER_URL}}","path":["api","currency",":currency"],"variable":[]},"auth":{"type":"bearer","bearer":[{"key":"token","value":"{{TOKEN_SERVER}}","type":"string"}]},"body":{"mode":"raw","raw":"\"{}\"","options":{"raw":{"language":"json"}}}},"event":[]},{"name":"api\/currency","request":{"method":"GET","header":[{"key":"Accept","value":"application\/json"},{"key":"Content-Type","value":"application\/json"},{"key":"x-lang","value":"es"}],"url":{"raw":"{{LOCAL_URL}}\/api\/auth\/login","host":"{{LOCAL_URL}}","path":["api","currency"],"variable":[]},"auth":{"type":"bearer","bearer":[{"key":"token","value":"{{TOKEN}}","type":"string"}]},"body":{"mode":"raw","raw":"\"{}\"","options":{"raw":{"language":"json"}}}},"event":[]},{"name":"api\/currency","request":{"method":"POST","header":[{"key":"Accept","value":"application\/json"},{"key":"Content-Type","value":"application\/json"},{"key":"x-lang","value":"es"}],"url":{"raw":"{{LOCAL_URL}}\/api\/auth\/login","host":"{{LOCAL_URL}}","path":["api","currency"],"variable":[]},"auth":{"type":"bearer","bearer":[{"key":"token","value":"{{TOKEN}}","type":"string"}]},"body":{"mode":"raw","raw":"{\"name\":\"{{$randomWords}}\",\"code\":\"{{$randomCountryCode}}\"}","options":{"raw":{"language":"json"}}}},"event":[]},{"name":"api\/currency\/{currency}","request":{"method":"DELETE","header":[{"key":"Accept","value":"application\/json"},{"key":"Content-Type","value":"application\/json"},{"key":"x-lang","value":"es"}],"url":{"raw":"{{LOCAL_URL}}\/api\/auth\/login","host":"{{LOCAL_URL}}","path":["api","currency",":currency"],"variable":[]},"auth":{"type":"bearer","bearer":[{"key":"token","value":"{{TOKEN}}","type":"string"}]},"body":{"mode":"raw","raw":"\"{}\"","options":{"raw":{"language":"json"}}}},"event":[]},{"name":"api\/currency\/{currency}","request":{"method":"GET","header":[{"key":"Accept","value":"application\/json"},{"key":"Content-Type","value":"application\/json"},{"key":"x-lang","value":"es"}],"url":{"raw":"{{LOCAL_URL}}\/api\/auth\/login","host":"{{LOCAL_URL}}","path":["api","currency",":currency"],"variable":[]},"auth":{"type":"bearer","bearer":[{"key":"token","value":"{{TOKEN}}","type":"string"}]},"body":{"mode":"raw","raw":"\"{}\"","options":{"raw":{"language":"json"}}}},"event":[]},{"name":"api\/currency\/{currency}","request":{"method":"PATCH","header":[{"key":"Accept","value":"application\/json"},{"key":"Content-Type","value":"application\/json"},{"key":"x-lang","value":"es"}],"url":{"raw":"{{LOCAL_URL}}\/api\/auth\/login","host":"{{LOCAL_URL}}","path":["api","currency",":currency"],"variable":[]},"auth":{"type":"bearer","bearer":[{"key":"token","value":"{{TOKEN}}","type":"string"}]},"body":{"mode":"raw","raw":"\"{}\"","options":{"raw":{"language":"json"}}}},"event":[]},{"name":"api\/currency\/{currency}","request":{"method":"PUT","header":[{"key":"Accept","value":"application\/json"},{"key":"Content-Type","value":"application\/json"},{"key":"x-lang","value":"es"}],"url":{"raw":"{{LOCAL_URL}}\/api\/auth\/login","host":"{{LOCAL_URL}}","path":["api","currency",":currency"],"variable":[]},"auth":{"type":"bearer","bearer":[{"key":"token","value":"{{TOKEN}}","type":"string"}]},"body":{"mode":"raw","raw":"\"{}\"","options":{"raw":{"language":"json"}}}},"event":[]}]},{"name":"state","item":[{"name":"SERVER_api\/state","request":{"method":"GET","header":[{"key":"Accept","value":"application\/json"},{"key":"Content-Type","value":"application\/json"},{"key":"x-lang","value":"es"}],"url":{"raw":"{{SERVER_URL}}\/api\/auth\/login","host":"{{SERVER_URL}}","path":["api","state"],"variable":[]},"auth":{"type":"bearer","bearer":[{"key":"token","value":"{{TOKEN_SERVER}}","type":"string"}]},"body":{"mode":"raw","raw":"\"{}\"","options":{"raw":{"language":"json"}}}},"event":[]},{"name":"SERVER_api\/state","request":{"method":"POST","header":[{"key":"Accept","value":"application\/json"},{"key":"Content-Type","value":"application\/json"},{"key":"x-lang","value":"es"}],"url":{"raw":"{{SERVER_URL}}\/api\/auth\/login","host":"{{SERVER_URL}}","path":["api","state"],"variable":[]},"auth":{"type":"bearer","bearer":[{"key":"token","value":"{{TOKEN_SERVER}}","type":"string"}]},"body":{"mode":"raw","raw":"{\"json_id\":\"{{INT10}}\",\"name\":\"{{$randomLoremParagraph}}\",\"country_code\":\"{{$randomLoremParagraph}}\",\"type\":\"{{$randomLoremParagraph}}\",\"latitude\":\"{{$randomLoremParagraph}}\",\"longitude\":\"{{$randomLoremParagraph}}\",\"country_id\":\"{{INT10}}\"}","options":{"raw":{"language":"json"}}}},"event":[]},{"name":"SERVER_api\/state\/{state}","request":{"method":"DELETE","header":[{"key":"Accept","value":"application\/json"},{"key":"Content-Type","value":"application\/json"},{"key":"x-lang","value":"es"}],"url":{"raw":"{{SERVER_URL}}\/api\/auth\/login","host":"{{SERVER_URL}}","path":["api","state",":state"],"variable":[]},"auth":{"type":"bearer","bearer":[{"key":"token","value":"{{TOKEN_SERVER}}","type":"string"}]},"body":{"mode":"raw","raw":"\"{}\"","options":{"raw":{"language":"json"}}}},"event":[]},{"name":"SERVER_api\/state\/{state}","request":{"method":"GET","header":[{"key":"Accept","value":"application\/json"},{"key":"Content-Type","value":"application\/json"},{"key":"x-lang","value":"es"}],"url":{"raw":"{{SERVER_URL}}\/api\/auth\/login","host":"{{SERVER_URL}}","path":["api","state",":state"],"variable":[]},"auth":{"type":"bearer","bearer":[{"key":"token","value":"{{TOKEN_SERVER}}","type":"string"}]},"body":{"mode":"raw","raw":"\"{}\"","options":{"raw":{"language":"json"}}}},"event":[]},{"name":"SERVER_api\/state\/{state}","request":{"method":"PATCH","header":[{"key":"Accept","value":"application\/json"},{"key":"Content-Type","value":"application\/json"},{"key":"x-lang","value":"es"}],"url":{"raw":"{{SERVER_URL}}\/api\/auth\/login","host":"{{SERVER_URL}}","path":["api","state",":state"],"variable":[]},"auth":{"type":"bearer","bearer":[{"key":"token","value":"{{TOKEN_SERVER}}","type":"string"}]},"body":{"mode":"raw","raw":"\"{}\"","options":{"raw":{"language":"json"}}}},"event":[]},{"name":"SERVER_api\/state\/{state}","request":{"method":"PUT","header":[{"key":"Accept","value":"application\/json"},{"key":"Content-Type","value":"application\/json"},{"key":"x-lang","value":"es"}],"url":{"raw":"{{SERVER_URL}}\/api\/auth\/login","host":"{{SERVER_URL}}","path":["api","state",":state"],"variable":[]},"auth":{"type":"bearer","bearer":[{"key":"token","value":"{{TOKEN_SERVER}}","type":"string"}]},"body":{"mode":"raw","raw":"\"{}\"","options":{"raw":{"language":"json"}}}},"event":[]},{"name":"api\/state","request":{"method":"GET","header":[{"key":"Accept","value":"application\/json"},{"key":"Content-Type","value":"application\/json"},{"key":"x-lang","value":"es"}],"url":{"raw":"{{LOCAL_URL}}\/api\/auth\/login","host":"{{LOCAL_URL}}","path":["api","state"],"variable":[]},"auth":{"type":"bearer","bearer":[{"key":"token","value":"{{TOKEN}}","type":"string"}]},"body":{"mode":"raw","raw":"\"{}\"","options":{"raw":{"language":"json"}}}},"event":[]},{"name":"api\/state","request":{"method":"POST","header":[{"key":"Accept","value":"application\/json"},{"key":"Content-Type","value":"application\/json"},{"key":"x-lang","value":"es"}],"url":{"raw":"{{LOCAL_URL}}\/api\/auth\/login","host":"{{LOCAL_URL}}","path":["api","state"],"variable":[]},"auth":{"type":"bearer","bearer":[{"key":"token","value":"{{TOKEN}}","type":"string"}]},"body":{"mode":"raw","raw":"{\"json_id\":\"{{INT10}}\",\"name\":\"{{$randomLoremParagraph}}\",\"country_code\":\"{{$randomLoremParagraph}}\",\"type\":\"{{$randomLoremParagraph}}\",\"latitude\":\"{{$randomLoremParagraph}}\",\"longitude\":\"{{$randomLoremParagraph}}\",\"country_id\":\"{{INT10}}\"}","options":{"raw":{"language":"json"}}}},"event":[]},{"name":"api\/state\/{state}","request":{"method":"DELETE","header":[{"key":"Accept","value":"application\/json"},{"key":"Content-Type","value":"application\/json"},{"key":"x-lang","value":"es"}],"url":{"raw":"{{LOCAL_URL}}\/api\/auth\/login","host":"{{LOCAL_URL}}","path":["api","state",":state"],"variable":[]},"auth":{"type":"bearer","bearer":[{"key":"token","value":"{{TOKEN}}","type":"string"}]},"body":{"mode":"raw","raw":"\"{}\"","options":{"raw":{"language":"json"}}}},"event":[]},{"name":"api\/state\/{state}","request":{"method":"GET","header":[{"key":"Accept","value":"application\/json"},{"key":"Content-Type","value":"application\/json"},{"key":"x-lang","value":"es"}],"url":{"raw":"{{LOCAL_URL}}\/api\/auth\/login","host":"{{LOCAL_URL}}","path":["api","state",":state"],"variable":[]},"auth":{"type":"bearer","bearer":[{"key":"token","value":"{{TOKEN}}","type":"string"}]},"body":{"mode":"raw","raw":"\"{}\"","options":{"raw":{"language":"json"}}}},"event":[]},{"name":"api\/state\/{state}","request":{"method":"PATCH","header":[{"key":"Accept","value":"application\/json"},{"key":"Content-Type","value":"application\/json"},{"key":"x-lang","value":"es"}],"url":{"raw":"{{LOCAL_URL}}\/api\/auth\/login","host":"{{LOCAL_URL}}","path":["api","state",":state"],"variable":[]},"auth":{"type":"bearer","bearer":[{"key":"token","value":"{{TOKEN}}","type":"string"}]},"body":{"mode":"raw","raw":"\"{}\"","options":{"raw":{"language":"json"}}}},"event":[]},{"name":"api\/state\/{state}","request":{"method":"PUT","header":[{"key":"Accept","value":"application\/json"},{"key":"Content-Type","value":"application\/json"},{"key":"x-lang","value":"es"}],"url":{"raw":"{{LOCAL_URL}}\/api\/auth\/login","host":"{{LOCAL_URL}}","path":["api","state",":state"],"variable":[]},"auth":{"type":"bearer","bearer":[{"key":"token","value":"{{TOKEN}}","type":"string"}]},"body":{"mode":"raw","raw":"\"{}\"","options":{"raw":{"language":"json"}}}},"event":[]}]},{"name":"user","item":[{"name":"SERVER_api\/user","request":{"method":"GET","header":[{"key":"Accept","value":"application\/json"},{"key":"Content-Type","value":"application\/json"},{"key":"x-lang","value":"es"}],"url":{"raw":"{{SERVER_URL}}\/api\/auth\/login","host":"{{SERVER_URL}}","path":["api","user"],"variable":[]},"auth":{"type":"bearer","bearer":[{"key":"token","value":"{{TOKEN_SERVER}}","type":"string"}]},"body":{"mode":"raw","raw":"\"{}\"","options":{"raw":{"language":"json"}}}},"event":[]},{"name":"SERVER_api\/user","request":{"method":"POST","header":[{"key":"Accept","value":"application\/json"},{"key":"Content-Type","value":"application\/json"},{"key":"x-lang","value":"es"}],"url":{"raw":"{{SERVER_URL}}\/api\/auth\/login","host":"{{SERVER_URL}}","path":["api","user"],"variable":[]},"auth":{"type":"bearer","bearer":[{"key":"token","value":"{{TOKEN_SERVER}}","type":"string"}]},"body":{"mode":"raw","raw":"{\"name\":\"{{$randomLoremSentence}}\",\"avatar\":\"{{$randomLoremParagraph}}\",\"active_directory_id\":\"{{INT10}}\",\"email\":\"{{$randomExampleEmail}}\",\"last_password_change\":\"\",\"password\":\"{{$randomLoremParagraph}}\",\"remember_token\":\"{{$randomLoremSentence}}\"}","options":{"raw":{"language":"json"}}}},"event":[]},{"name":"SERVER_api\/user\/{user}","request":{"method":"DELETE","header":[{"key":"Accept","value":"application\/json"},{"key":"Content-Type","value":"application\/json"},{"key":"x-lang","value":"es"}],"url":{"raw":"{{SERVER_URL}}\/api\/auth\/login","host":"{{SERVER_URL}}","path":["api","user",":user"],"variable":[]},"auth":{"type":"bearer","bearer":[{"key":"token","value":"{{TOKEN_SERVER}}","type":"string"}]},"body":{"mode":"raw","raw":"\"{}\"","options":{"raw":{"language":"json"}}}},"event":[]},{"name":"SERVER_api\/user\/{user}","request":{"method":"GET","header":[{"key":"Accept","value":"application\/json"},{"key":"Content-Type","value":"application\/json"},{"key":"x-lang","value":"es"}],"url":{"raw":"{{SERVER_URL}}\/api\/auth\/login","host":"{{SERVER_URL}}","path":["api","user",":user"],"variable":[]},"auth":{"type":"bearer","bearer":[{"key":"token","value":"{{TOKEN_SERVER}}","type":"string"}]},"body":{"mode":"raw","raw":"\"{}\"","options":{"raw":{"language":"json"}}}},"event":[]},{"name":"SERVER_api\/user\/{user}","request":{"method":"PATCH","header":[{"key":"Accept","value":"application\/json"},{"key":"Content-Type","value":"application\/json"},{"key":"x-lang","value":"es"}],"url":{"raw":"{{SERVER_URL}}\/api\/auth\/login","host":"{{SERVER_URL}}","path":["api","user",":user"],"variable":[]},"auth":{"type":"bearer","bearer":[{"key":"token","value":"{{TOKEN_SERVER}}","type":"string"}]},"body":{"mode":"raw","raw":"\"{}\"","options":{"raw":{"language":"json"}}}},"event":[]},{"name":"SERVER_api\/user\/{user}","request":{"method":"PUT","header":[{"key":"Accept","value":"application\/json"},{"key":"Content-Type","value":"application\/json"},{"key":"x-lang","value":"es"}],"url":{"raw":"{{SERVER_URL}}\/api\/auth\/login","host":"{{SERVER_URL}}","path":["api","user",":user"],"variable":[]},"auth":{"type":"bearer","bearer":[{"key":"token","value":"{{TOKEN_SERVER}}","type":"string"}]},"body":{"mode":"raw","raw":"\"{}\"","options":{"raw":{"language":"json"}}}},"event":[]},{"name":"api\/user","request":{"method":"GET","header":[{"key":"Accept","value":"application\/json"},{"key":"Content-Type","value":"application\/json"},{"key":"x-lang","value":"es"}],"url":{"raw":"{{LOCAL_URL}}\/api\/auth\/login","host":"{{LOCAL_URL}}","path":["api","user"],"variable":[]},"auth":{"type":"bearer","bearer":[{"key":"token","value":"{{TOKEN}}","type":"string"}]},"body":{"mode":"raw","raw":"\"{}\"","options":{"raw":{"language":"json"}}}},"event":[]},{"name":"api\/user","request":{"method":"POST","header":[{"key":"Accept","value":"application\/json"},{"key":"Content-Type","value":"application\/json"},{"key":"x-lang","value":"es"}],"url":{"raw":"{{LOCAL_URL}}\/api\/auth\/login","host":"{{LOCAL_URL}}","path":["api","user"],"variable":[]},"auth":{"type":"bearer","bearer":[{"key":"token","value":"{{TOKEN}}","type":"string"}]},"body":{"mode":"raw","raw":"{\"name\":\"{{$randomLoremSentence}}\",\"avatar\":\"{{$randomLoremParagraph}}\",\"active_directory_id\":\"{{INT10}}\",\"email\":\"{{$randomExampleEmail}}\",\"last_password_change\":\"\",\"password\":\"{{$randomLoremParagraph}}\",\"remember_token\":\"{{$randomLoremSentence}}\"}","options":{"raw":{"language":"json"}}}},"event":[]},{"name":"api\/user\/{user}","request":{"method":"DELETE","header":[{"key":"Accept","value":"application\/json"},{"key":"Content-Type","value":"application\/json"},{"key":"x-lang","value":"es"}],"url":{"raw":"{{LOCAL_URL}}\/api\/auth\/login","host":"{{LOCAL_URL}}","path":["api","user",":user"],"variable":[]},"auth":{"type":"bearer","bearer":[{"key":"token","value":"{{TOKEN}}","type":"string"}]},"body":{"mode":"raw","raw":"\"{}\"","options":{"raw":{"language":"json"}}}},"event":[]},{"name":"api\/user\/{user}","request":{"method":"GET","header":[{"key":"Accept","value":"application\/json"},{"key":"Content-Type","value":"application\/json"},{"key":"x-lang","value":"es"}],"url":{"raw":"{{LOCAL_URL}}\/api\/auth\/login","host":"{{LOCAL_URL}}","path":["api","user",":user"],"variable":[]},"auth":{"type":"bearer","bearer":[{"key":"token","value":"{{TOKEN}}","type":"string"}]},"body":{"mode":"raw","raw":"\"{}\"","options":{"raw":{"language":"json"}}}},"event":[]},{"name":"api\/user\/{user}","request":{"method":"PATCH","header":[{"key":"Accept","value":"application\/json"},{"key":"Content-Type","value":"application\/json"},{"key":"x-lang","value":"es"}],"url":{"raw":"{{LOCAL_URL}}\/api\/auth\/login","host":"{{LOCAL_URL}}","path":["api","user",":user"],"variable":[]},"auth":{"type":"bearer","bearer":[{"key":"token","value":"{{TOKEN}}","type":"string"}]},"body":{"mode":"raw","raw":"\"{}\"","options":{"raw":{"language":"json"}}}},"event":[]},{"name":"api\/user\/{user}","request":{"method":"PUT","header":[{"key":"Accept","value":"application\/json"},{"key":"Content-Type","value":"application\/json"},{"key":"x-lang","value":"es"}],"url":{"raw":"{{LOCAL_URL}}\/api\/auth\/login","host":"{{LOCAL_URL}}","path":["api","user",":user"],"variable":[]},"auth":{"type":"bearer","bearer":[{"key":"token","value":"{{TOKEN}}","type":"string"}]},"body":{"mode":"raw","raw":"\"{}\"","options":{"raw":{"language":"json"}}}},"event":[]}]},{"name":"role","item":[{"name":"SERVER_api\/role","request":{"method":"GET","header":[{"key":"Accept","value":"application\/json"},{"key":"Content-Type","value":"application\/json"},{"key":"x-lang","value":"es"}],"url":{"raw":"{{SERVER_URL}}\/api\/auth\/login","host":"{{SERVER_URL}}","path":["api","role"],"variable":[]},"auth":{"type":"bearer","bearer":[{"key":"token","value":"{{TOKEN_SERVER}}","type":"string"}]},"body":{"mode":"raw","raw":"\"{}\"","options":{"raw":{"language":"json"}}}},"event":[]},{"name":"SERVER_api\/role","request":{"method":"POST","header":[{"key":"Accept","value":"application\/json"},{"key":"Content-Type","value":"application\/json"},{"key":"x-lang","value":"es"}],"url":{"raw":"{{SERVER_URL}}\/api\/auth\/login","host":"{{SERVER_URL}}","path":["api","role"],"variable":[]},"auth":{"type":"bearer","bearer":[{"key":"token","value":"{{TOKEN_SERVER}}","type":"string"}]},"body":{"mode":"raw","raw":"{\"name\":\"{{$randomLoremParagraph}}\",\"guard_name\":\"{{$randomLoremParagraph}}\"}","options":{"raw":{"language":"json"}}}},"event":[]},{"name":"SERVER_api\/role\/{role}","request":{"method":"DELETE","header":[{"key":"Accept","value":"application\/json"},{"key":"Content-Type","value":"application\/json"},{"key":"x-lang","value":"es"}],"url":{"raw":"{{SERVER_URL}}\/api\/auth\/login","host":"{{SERVER_URL}}","path":["api","role",":role"],"variable":[]},"auth":{"type":"bearer","bearer":[{"key":"token","value":"{{TOKEN_SERVER}}","type":"string"}]},"body":{"mode":"raw","raw":"\"{}\"","options":{"raw":{"language":"json"}}}},"event":[]},{"name":"SERVER_api\/role\/{role}","request":{"method":"GET","header":[{"key":"Accept","value":"application\/json"},{"key":"Content-Type","value":"application\/json"},{"key":"x-lang","value":"es"}],"url":{"raw":"{{SERVER_URL}}\/api\/auth\/login","host":"{{SERVER_URL}}","path":["api","role",":role"],"variable":[]},"auth":{"type":"bearer","bearer":[{"key":"token","value":"{{TOKEN_SERVER}}","type":"string"}]},"body":{"mode":"raw","raw":"\"{}\"","options":{"raw":{"language":"json"}}}},"event":[]},{"name":"SERVER_api\/role\/{role}","request":{"method":"PATCH","header":[{"key":"Accept","value":"application\/json"},{"key":"Content-Type","value":"application\/json"},{"key":"x-lang","value":"es"}],"url":{"raw":"{{SERVER_URL}}\/api\/auth\/login","host":"{{SERVER_URL}}","path":["api","role",":role"],"variable":[]},"auth":{"type":"bearer","bearer":[{"key":"token","value":"{{TOKEN_SERVER}}","type":"string"}]},"body":{"mode":"raw","raw":"\"{}\"","options":{"raw":{"language":"json"}}}},"event":[]},{"name":"SERVER_api\/role\/{role}","request":{"method":"PUT","header":[{"key":"Accept","value":"application\/json"},{"key":"Content-Type","value":"application\/json"},{"key":"x-lang","value":"es"}],"url":{"raw":"{{SERVER_URL}}\/api\/auth\/login","host":"{{SERVER_URL}}","path":["api","role",":role"],"variable":[]},"auth":{"type":"bearer","bearer":[{"key":"token","value":"{{TOKEN_SERVER}}","type":"string"}]},"body":{"mode":"raw","raw":"\"{}\"","options":{"raw":{"language":"json"}}}},"event":[]},{"name":"api\/role","request":{"method":"GET","header":[{"key":"Accept","value":"application\/json"},{"key":"Content-Type","value":"application\/json"},{"key":"x-lang","value":"es"}],"url":{"raw":"{{LOCAL_URL}}\/api\/auth\/login","host":"{{LOCAL_URL}}","path":["api","role"],"variable":[]},"auth":{"type":"bearer","bearer":[{"key":"token","value":"{{TOKEN}}","type":"string"}]},"body":{"mode":"raw","raw":"\"{}\"","options":{"raw":{"language":"json"}}}},"event":[]},{"name":"api\/role","request":{"method":"POST","header":[{"key":"Accept","value":"application\/json"},{"key":"Content-Type","value":"application\/json"},{"key":"x-lang","value":"es"}],"url":{"raw":"{{LOCAL_URL}}\/api\/auth\/login","host":"{{LOCAL_URL}}","path":["api","role"],"variable":[]},"auth":{"type":"bearer","bearer":[{"key":"token","value":"{{TOKEN}}","type":"string"}]},"body":{"mode":"raw","raw":"{\"name\":\"{{$randomLoremParagraph}}\",\"guard_name\":\"{{$randomLoremParagraph}}\"}","options":{"raw":{"language":"json"}}}},"event":[]},{"name":"api\/role\/{role}","request":{"method":"DELETE","header":[{"key":"Accept","value":"application\/json"},{"key":"Content-Type","value":"application\/json"},{"key":"x-lang","value":"es"}],"url":{"raw":"{{LOCAL_URL}}\/api\/auth\/login","host":"{{LOCAL_URL}}","path":["api","role",":role"],"variable":[]},"auth":{"type":"bearer","bearer":[{"key":"token","value":"{{TOKEN}}","type":"string"}]},"body":{"mode":"raw","raw":"\"{}\"","options":{"raw":{"language":"json"}}}},"event":[]},{"name":"api\/role\/{role}","request":{"method":"GET","header":[{"key":"Accept","value":"application\/json"},{"key":"Content-Type","value":"application\/json"},{"key":"x-lang","value":"es"}],"url":{"raw":"{{LOCAL_URL}}\/api\/auth\/login","host":"{{LOCAL_URL}}","path":["api","role",":role"],"variable":[]},"auth":{"type":"bearer","bearer":[{"key":"token","value":"{{TOKEN}}","type":"string"}]},"body":{"mode":"raw","raw":"\"{}\"","options":{"raw":{"language":"json"}}}},"event":[]},{"name":"api\/role\/{role}","request":{"method":"PATCH","header":[{"key":"Accept","value":"application\/json"},{"key":"Content-Type","value":"application\/json"},{"key":"x-lang","value":"es"}],"url":{"raw":"{{LOCAL_URL}}\/api\/auth\/login","host":"{{LOCAL_URL}}","path":["api","role",":role"],"variable":[]},"auth":{"type":"bearer","bearer":[{"key":"token","value":"{{TOKEN}}","type":"string"}]},"body":{"mode":"raw","raw":"\"{}\"","options":{"raw":{"language":"json"}}}},"event":[]},{"name":"api\/role\/{role}","request":{"method":"PUT","header":[{"key":"Accept","value":"application\/json"},{"key":"Content-Type","value":"application\/json"},{"key":"x-lang","value":"es"}],"url":{"raw":"{{LOCAL_URL}}\/api\/auth\/login","host":"{{LOCAL_URL}}","path":["api","role",":role"],"variable":[]},"auth":{"type":"bearer","bearer":[{"key":"token","value":"{{TOKEN}}","type":"string"}]},"body":{"mode":"raw","raw":"\"{}\"","options":{"raw":{"language":"json"}}}},"event":[]}]},{"name":"city","item":[{"name":"SERVER_api\/city","request":{"method":"GET","header":[{"key":"Accept","value":"application\/json"},{"key":"Content-Type","value":"application\/json"},{"key":"x-lang","value":"es"}],"url":{"raw":"{{SERVER_URL}}\/api\/auth\/login","host":"{{SERVER_URL}}","path":["api","city"],"variable":[]},"auth":{"type":"bearer","bearer":[{"key":"token","value":"{{TOKEN_SERVER}}","type":"string"}]},"body":{"mode":"raw","raw":"\"{}\"","options":{"raw":{"language":"json"}}}},"event":[]},{"name":"SERVER_api\/city","request":{"method":"POST","header":[{"key":"Accept","value":"application\/json"},{"key":"Content-Type","value":"application\/json"},{"key":"x-lang","value":"es"}],"url":{"raw":"{{SERVER_URL}}\/api\/auth\/login","host":"{{SERVER_URL}}","path":["api","city"],"variable":[]},"auth":{"type":"bearer","bearer":[{"key":"token","value":"{{TOKEN_SERVER}}","type":"string"}]},"body":{"mode":"raw","raw":"{\"json_id\":\"{{INT10}}\",\"name\":\"{{$randomLoremParagraph}}\",\"state_code\":\"{{$randomLoremParagraph}}\",\"country_code\":\"{{$randomLoremParagraph}}\",\"latitude\":\"{{$randomLoremParagraph}}\",\"longitude\":\"{{$randomLoremParagraph}}\",\"wikiDataId\":\"{{$randomLoremParagraph}}\",\"state_id\":\"{{INT10}}\",\"country_id\":\"{{INT10}}\"}","options":{"raw":{"language":"json"}}}},"event":[]},{"name":"SERVER_api\/city\/{city}","request":{"method":"DELETE","header":[{"key":"Accept","value":"application\/json"},{"key":"Content-Type","value":"application\/json"},{"key":"x-lang","value":"es"}],"url":{"raw":"{{SERVER_URL}}\/api\/auth\/login","host":"{{SERVER_URL}}","path":["api","city",":city"],"variable":[]},"auth":{"type":"bearer","bearer":[{"key":"token","value":"{{TOKEN_SERVER}}","type":"string"}]},"body":{"mode":"raw","raw":"\"{}\"","options":{"raw":{"language":"json"}}}},"event":[]},{"name":"SERVER_api\/city\/{city}","request":{"method":"GET","header":[{"key":"Accept","value":"application\/json"},{"key":"Content-Type","value":"application\/json"},{"key":"x-lang","value":"es"}],"url":{"raw":"{{SERVER_URL}}\/api\/auth\/login","host":"{{SERVER_URL}}","path":["api","city",":city"],"variable":[]},"auth":{"type":"bearer","bearer":[{"key":"token","value":"{{TOKEN_SERVER}}","type":"string"}]},"body":{"mode":"raw","raw":"\"{}\"","options":{"raw":{"language":"json"}}}},"event":[]},{"name":"SERVER_api\/city\/{city}","request":{"method":"PATCH","header":[{"key":"Accept","value":"application\/json"},{"key":"Content-Type","value":"application\/json"},{"key":"x-lang","value":"es"}],"url":{"raw":"{{SERVER_URL}}\/api\/auth\/login","host":"{{SERVER_URL}}","path":["api","city",":city"],"variable":[]},"auth":{"type":"bearer","bearer":[{"key":"token","value":"{{TOKEN_SERVER}}","type":"string"}]},"body":{"mode":"raw","raw":"\"{}\"","options":{"raw":{"language":"json"}}}},"event":[]},{"name":"SERVER_api\/city\/{city}","request":{"method":"PUT","header":[{"key":"Accept","value":"application\/json"},{"key":"Content-Type","value":"application\/json"},{"key":"x-lang","value":"es"}],"url":{"raw":"{{SERVER_URL}}\/api\/auth\/login","host":"{{SERVER_URL}}","path":["api","city",":city"],"variable":[]},"auth":{"type":"bearer","bearer":[{"key":"token","value":"{{TOKEN_SERVER}}","type":"string"}]},"body":{"mode":"raw","raw":"\"{}\"","options":{"raw":{"language":"json"}}}},"event":[]},{"name":"api\/city","request":{"method":"GET","header":[{"key":"Accept","value":"application\/json"},{"key":"Content-Type","value":"application\/json"},{"key":"x-lang","value":"es"}],"url":{"raw":"{{LOCAL_URL}}\/api\/auth\/login","host":"{{LOCAL_URL}}","path":["api","city"],"variable":[]},"auth":{"type":"bearer","bearer":[{"key":"token","value":"{{TOKEN}}","type":"string"}]},"body":{"mode":"raw","raw":"\"{}\"","options":{"raw":{"language":"json"}}}},"event":[]},{"name":"api\/city","request":{"method":"POST","header":[{"key":"Accept","value":"application\/json"},{"key":"Content-Type","value":"application\/json"},{"key":"x-lang","value":"es"}],"url":{"raw":"{{LOCAL_URL}}\/api\/auth\/login","host":"{{LOCAL_URL}}","path":["api","city"],"variable":[]},"auth":{"type":"bearer","bearer":[{"key":"token","value":"{{TOKEN}}","type":"string"}]},"body":{"mode":"raw","raw":"{\"json_id\":\"{{INT10}}\",\"name\":\"{{$randomLoremParagraph}}\",\"state_code\":\"{{$randomLoremParagraph}}\",\"country_code\":\"{{$randomLoremParagraph}}\",\"latitude\":\"{{$randomLoremParagraph}}\",\"longitude\":\"{{$randomLoremParagraph}}\",\"wikiDataId\":\"{{$randomLoremParagraph}}\",\"state_id\":\"{{INT10}}\",\"country_id\":\"{{INT10}}\"}","options":{"raw":{"language":"json"}}}},"event":[]},{"name":"api\/city\/{city}","request":{"method":"DELETE","header":[{"key":"Accept","value":"application\/json"},{"key":"Content-Type","value":"application\/json"},{"key":"x-lang","value":"es"}],"url":{"raw":"{{LOCAL_URL}}\/api\/auth\/login","host":"{{LOCAL_URL}}","path":["api","city",":city"],"variable":[]},"auth":{"type":"bearer","bearer":[{"key":"token","value":"{{TOKEN}}","type":"string"}]},"body":{"mode":"raw","raw":"\"{}\"","options":{"raw":{"language":"json"}}}},"event":[]},{"name":"api\/city\/{city}","request":{"method":"GET","header":[{"key":"Accept","value":"application\/json"},{"key":"Content-Type","value":"application\/json"},{"key":"x-lang","value":"es"}],"url":{"raw":"{{LOCAL_URL}}\/api\/auth\/login","host":"{{LOCAL_URL}}","path":["api","city",":city"],"variable":[]},"auth":{"type":"bearer","bearer":[{"key":"token","value":"{{TOKEN}}","type":"string"}]},"body":{"mode":"raw","raw":"\"{}\"","options":{"raw":{"language":"json"}}}},"event":[]},{"name":"api\/city\/{city}","request":{"method":"PATCH","header":[{"key":"Accept","value":"application\/json"},{"key":"Content-Type","value":"application\/json"},{"key":"x-lang","value":"es"}],"url":{"raw":"{{LOCAL_URL}}\/api\/auth\/login","host":"{{LOCAL_URL}}","path":["api","city",":city"],"variable":[]},"auth":{"type":"bearer","bearer":[{"key":"token","value":"{{TOKEN}}","type":"string"}]},"body":{"mode":"raw","raw":"\"{}\"","options":{"raw":{"language":"json"}}}},"event":[]},{"name":"api\/city\/{city}","request":{"method":"PUT","header":[{"key":"Accept","value":"application\/json"},{"key":"Content-Type","value":"application\/json"},{"key":"x-lang","value":"es"}],"url":{"raw":"{{LOCAL_URL}}\/api\/auth\/login","host":"{{LOCAL_URL}}","path":["api","city",":city"],"variable":[]},"auth":{"type":"bearer","bearer":[{"key":"token","value":"{{TOKEN}}","type":"string"}]},"body":{"mode":"raw","raw":"\"{}\"","options":{"raw":{"language":"json"}}}},"event":[]}]}],"event":[{"listen":"prerequest","script":{"type":"text\/javascript","exec":["pm.collectionVariables.set(\"INT5\", Math.floor(Math.random()*5))","pm.collectionVariables.set(\"INT10\", Math.floor(Math.random()*10))","pm.collectionVariables.set(\"INT50\", Math.floor(Math.random()*50))","pm.collectionVariables.set(\"INT100\", Math.floor(Math.random()*100))","pm.collectionVariables.set(\"BOOLEAN\", Math.floor(Math.random()*2))","function randomDate(start, end) {","        return new Date(start.getTime() + Math.random() * (end.getTime() - start.getTime()));","}","var date = randomDate(new Date(2000, 0, 1), new Date());","var year_last_integer = Math.floor(Math.random() * 10);","const month = date.getMonth()+1;","const real_month = month < 10? `0${month}`: month;","var formattedDate =  '199' + year_last_integer + '\/' +real_month + '\/' + date.getDate();","pm.collectionVariables.set(\"date\", formattedDate)","","",""]}},{"listen":"test","script":{"type":"text\/javascript","exec":[""]}}]}